temaselectsysten/__init__.py
temaselectsysten/mytheme.txt
temaselectsysten/Tema.json
temaselectsysten/TemaSelectSysten.py
temaselectsysten-0.1.10.dist-info/METADATA
temaselectsysten-0.1.10.dist-info/WHEEL
temaselectsysten-0.1.10.dist-info/RECORD
