Metadata-Version: 2.1
Name: temaselectsysten
Version: 0.1.10
Summary: 
Author: leomoraesguitar
Author-email: 123950901+leomoraesguitar@users.noreply.github.com
Requires-Python: >=3.8,<4.0
Classifier: Programming Language :: Python :: 3
Classifier: Programming Language :: Python :: 3.8
Classifier: Programming Language :: Python :: 3.9
Classifier: Programming Language :: Python :: 3.10
Classifier: Programming Language :: Python :: 3.11
Classifier: Programming Language :: Python :: 3.12
Requires-Dist: flet (>=0.24.1,<0.25.0)
